{
  "slug": "1-5-2-the-relative-importance-and-influence-of-stakeholders-on-business-activities",
  "topicCode": "1.5.2",
  "title": "The relative importance and influence of stakeholders on business activities",
  "paper": "AS",
  "paperName": "AS Level Content (Paper 1 & 2)",
  "status": "premium",
  "summary": "9609 AS — stakeholder power, interest, and conflict over decisions.",
  "durationMin": 20,
  "updated": "2026-06-10",
  "learningObjectives": [
    "Identify key stakeholder groups.",
    "Assess relative power and influence.",
    "Explain stakeholder conflicts.",
    "Evaluate how firms balance stakeholder demands."
  ],
  "simpleExplanation": {
    "title": "Who pulls the strings?",
    "summary": "Stakeholders differ in how much they can affect or are affected by a business. Managers must weigh their competing interests.",
    "steps": [
      "Shareholders want profit and dividends.",
      "Employees want pay and job security.",
      "Customers want quality and value.",
      "Community and government add pressure."
    ]
  },
  "sections": [
    { "type": "intro", "content": "**Stakeholder influence** (1.5.2) extends **1.5.1**. Use a **power/interest matrix** mindset in case evaluation." },
    { "type": "practice", "label": "Mark a stakeholder influence question", "href": "/mark?subject=9609&topic=1.5.2" },
    { "type": "resources", "items": [{ "label": "9609 course index", "href": "/courses/9609" }] }
  ]
}
