{
  "slug": "7-3-1-leadership",
  "topicCode": "7.3.1",
  "title": "Leadership",
  "paper": "AL",
  "paperName": "A Level Content (Paper 3 & 4)",
  "status": "premium",
  "summary": "9609 A Level — leadership roles, styles, and impact on organisational performance.",
  "durationMin": 22,
  "updated": "2026-06-10",
  "learningObjectives": [
    "Define leadership and distinguish from management.",
    "Describe key leadership functions.",
    "Analyse impact on culture and change.",
    "Evaluate leadership in case organisations."
  ],
  "simpleExplanation": {
    "title": "Inspiring direction",
    "summary": "Leadership sets vision, motivates people, and drives change. It complements management's focus on planning and control.",
    "steps": [
      "Vision and strategic direction.",
      "Motivate and inspire commitment.",
      "Lead change programmes.",
      "Build trust with stakeholders."
    ]
  },
  "sections": [
    { "type": "intro", "content": "**Leadership** (7.3.1) opens **7.3**. Contrast **leader vs manager** using case examples." },
    { "type": "practice", "label": "Mark a leadership question", "href": "/mark?subject=9609&topic=7.3.1" },
    { "type": "resources", "items": [{ "label": "9609 course index", "href": "/courses/9609" }] }
  ]
}
