{
  "slug": "13-2-file-organisation-and-access",
  "topicCode": "13.2",
  "title": "File organisation and access",
  "paper": "AL",
  "paperName": "A Level Subject Content",
  "status": "premium",
  "summary": "9618 A Level file organisation — sequential, random, indexed-sequential access methods.",
  "durationMin": 20,
  "updated": "2026-06-10",
  "learningObjectives": [
    "Compare sequential and random file organisation.",
    "Explain indexed-sequential files.",
    "Evaluate access methods for given scenarios.",
    "Relate file design to processing requirements."
  ],
  "simpleExplanation": {
    "title": "How records are stored and found",
    "summary": "File organisation trades storage efficiency against speed of access for different processing patterns.",
    "steps": [
      "Sequential: records in order, batch processing.",
      "Random/direct: hash or key maps to location.",
      "Indexed-sequential: index speeds lookup in ordered file.",
      "Choose method based on read/write frequency."
    ]
  },
  "sections": [
    { "type": "intro", "content": "**File organisation** (13.2) extends **13.1 file concepts**. Match **access method** to **application scenario**." },
    { "type": "practice", "label": "Mark a file organisation question", "href": "/mark?subject=9618&topic=13.2" },
    { "type": "resources", "items": [{ "label": "9618 course index", "href": "/courses/9618" }] }
  ]
}
