{
  "slug": "2-3-trigonometry",
  "topicCode": "2.3",
  "title": "Trigonometry",
  "paper": "P2",
  "paperName": "Pure Mathematics 2",
  "status": "premium",
  "summary": "9709 P2 trigonometry — identities, equations, and R sin(θ + α) form with GeoGebra unit circle.",
  "durationMin": 22,
  "updated": "2026-06-10",
  "learningObjectives": [
    "Use compound angle and double angle formulae.",
    "Solve trigonometric equations in a given interval.",
    "Express a sin θ + b cos θ in the form R sin(θ + α).",
    "Prove identities using known relationships."
  ],
  "simpleExplanation": {
    "title": "P2 trig beyond P1",
    "summary": "P2 adds compound angles and more complex equations. The R-formula compresses a sin θ + b cos θ into a single sine wave.",
    "steps": [
      "sin(A ± B), cos(A ± B) — expand carefully with signs.",
      "Double angle: sin 2A = 2 sin A cos A.",
      "R sin(θ + α): R = √(a² + b²), tan α = b/a (quadrant matters).",
      "General solutions — count roots in [0, 2π) or given range."
    ]
  },
  "sections": [
    {
      "type": "intro",
      "content": "**P2 Trigonometry** (2.3) builds on **P1 trig** (1.5). Examiners love **identity proofs** — start from the **more complex side**."
    },
    {
      "type": "practice",
      "label": "Mark a P2 trigonometry question",
      "href": "/mark?subject=9709&topic=2.3"
    },
    {
      "type": "resources",
      "items": [{ "label": "9709 course index", "href": "/courses/9709" }]
    }
  ]
}
