{
  "slug": "6-3-ethnicity-and-educational-attainment",
  "topicCode": "6.3",
  "title": "Ethnicity and educational attainment",
  "paper": "P3",
  "paperName": "Paper 3: Education",
  "status": "premium",
  "summary": "9699 — ethnic differences in achievement, racism, and cultural factors in education.",
  "durationMin": 24,
  "updated": "2026-06-10",
  "learningObjectives": [
    "Describe patterns of achievement by ethnic group.",
    "Explain material and cultural factors for ethnic minorities.",
    "Analyse institutional racism and teacher labelling.",
    "Evaluate policy responses to ethnic inequality."
  ],
  "simpleExplanation": {
    "title": "Ethnicity and exam results",
    "summary": "Achievement varies widely by ethnic group — material disadvantage, family culture, and racism in schools all play a part.",
    "steps": [
      "Patterns — e.g. Chinese/Indian high; some groups lower.",
      "Cultural factors — family values, language.",
      "Racism — Gillborn, Wright, Mac an Ghaill.",
      "Anti-racist education and EAL support."
    ]
  },
  "sections": [
    { "type": "intro", "content": "**Ethnicity and attainment** (6.3) needs **nuanced statistics** — avoid stereotypes; explain **within-group variation**." },
    { "type": "practice", "label": "Mark an ethnicity attainment question", "href": "/mark?subject=9699&topic=6.3" },
    { "type": "resources", "items": [{ "label": "9699 course index", "href": "/courses/9699" }] }
  ]
}
