{
  "subjectCode": "ib-computer-science-hl",
  "subjectName": "Computer Science",
  "level": "Higher Level",
  "syllabusYear": 2014,
  "note": "IB Diploma Computer Science HL (established syllabus). Core topics 1-4 (system fundamentals, computer organization, networks, computational thinking & programming), HL extension topics 5-7 (abstract data structures, resource management, control), plus the Object-Oriented Programming option. Lessons are curated concept clusters; codes 1.1-8.3 sort in syllabus order. Factual syllabus structure only.",
  "topics": [
    { "code": "1.1", "name": "Systems in organizations: planning and change management", "paper": "P1", "paperName": "Computer Science HL" },
    { "code": "1.2", "name": "System design basics: components, usability and documentation", "paper": "P1", "paperName": "Computer Science HL" },
    { "code": "2.1", "name": "Computer architecture: the CPU and primary memory", "paper": "P1", "paperName": "Computer Science HL" },
    { "code": "2.2", "name": "Secondary memory and operating systems", "paper": "P1", "paperName": "Computer Science HL" },
    { "code": "2.3", "name": "Binary representation of data", "paper": "P1", "paperName": "Computer Science HL" },
    { "code": "3.1", "name": "Network fundamentals", "paper": "P1", "paperName": "Computer Science HL" },
    { "code": "3.2", "name": "Data transmission and wireless networks", "paper": "P1", "paperName": "Computer Science HL" },
    { "code": "4.1", "name": "Computational thinking: abstraction, decomposition and algorithms", "paper": "P1", "paperName": "Computer Science HL" },
    { "code": "4.2", "name": "Connecting computational thinking and program design", "paper": "P1", "paperName": "Computer Science HL" },
    { "code": "4.3", "name": "Introduction to programming: variables, control and methods", "paper": "P1", "paperName": "Computer Science HL" },
    { "code": "4.4", "name": "Flowcharts, pseudocode and algorithm design", "paper": "P1", "paperName": "Computer Science HL" },
    { "code": "5.1", "name": "Abstract data structures: recursion and the stack", "paper": "P1", "paperName": "Computer Science HL" },
    { "code": "5.2", "name": "Linked lists", "paper": "P1", "paperName": "Computer Science HL" },
    { "code": "5.3", "name": "Trees and binary trees", "paper": "P1", "paperName": "Computer Science HL" },
    { "code": "5.4", "name": "Stacks, queues and the application of data structures", "paper": "P1", "paperName": "Computer Science HL" },
    { "code": "6.1", "name": "Resource management: system resources and scheduling", "paper": "P1", "paperName": "Computer Science HL" },
    { "code": "6.2", "name": "Memory management and virtual memory", "paper": "P1", "paperName": "Computer Science HL" },
    { "code": "7.1", "name": "Control systems: sensors, actuators and feedback", "paper": "P1", "paperName": "Computer Science HL" },
    { "code": "7.2", "name": "Embedded systems and microprocessors", "paper": "P1", "paperName": "Computer Science HL" },
    { "code": "8.1", "name": "Object-oriented programming: classes, objects and encapsulation", "paper": "P2", "paperName": "Computer Science HL" },
    { "code": "8.2", "name": "Inheritance, polymorphism and abstraction", "paper": "P2", "paperName": "Computer Science HL" },
    { "code": "8.3", "name": "OOP program design and UML", "paper": "P2", "paperName": "Computer Science HL" }
  ]
}
