{
  "slug": "6-4-exchange-rates",
  "topicCode": "6.4",
  "title": "Exchange rates",
  "paper": "AS",
  "paperName": "Cambridge International AS Level Economics (P1 & P2)",
  "status": "premium",
  "summary": "9708 AS exchange rates — floating and fixed systems, appreciation, depreciation, and effects on trade with GeoGebra.",
  "durationMin": 22,
  "updated": "2026-06-10",
  "learningObjectives": [
    "Define exchange rate and distinguish floating from fixed systems.",
    "Explain causes of currency appreciation and depreciation.",
    "Analyse effects on exports, imports, and AD.",
    "Describe central bank intervention in forex markets."
  ],
  "simpleExplanation": {
    "title": "Price of a currency",
    "summary": "Under floating rates, supply and demand for a currency set its price. Depreciation makes exports cheaper abroad and imports dearer at home.",
    "steps": [
      "Appreciation: currency buys more foreign currency — ↑ import spending power.",
      "Depreciation: boosts X competitiveness, raises M prices in domestic terms.",
      "Demand for £ from foreigners buying UK goods/investments.",
      "Fixed rate: central bank buys/sells reserves to maintain peg."
    ]
  },
  "sections": [
    {
      "type": "intro",
      "content": "**Exchange rates** (6.4) feature in **J-curve** and **Marshall–Lerner** discussions at A Level. At AS, focus on **AD transmission** via (X−M)."
    },
    {
      "type": "practice",
      "label": "Mark an exchange rates question",
      "href": "/mark?subject=9708&topic=6.4"
    },
    {
      "type": "resources",
      "items": [{ "label": "9708 course index", "href": "/courses/9708" }]
    }
  ]
}
